django_ses/__init__.py
django_ses/apps.py
django_ses/models.py
django_ses/views.py
django_ses/migrations/__init__.py
django_ses_email_backend-0.0.1.dist-info/METADATA
django_ses_email_backend-0.0.1.dist-info/RECORD
django_ses_email_backend-0.0.1.dist-info/WHEEL
django_ses_email_backend-0.0.1.dist-info/top_level.txt
