Metadata-Version: 2.1
Name: django-ses-email-backend
Version: 0.0.1
Summary: A Drop in Replacement for default django email backend based on Amazon SES
Home-page: https://github.com/ppshobi/django-ses
Author: Shobi P P
Author-email: ppshobi@gmail.com
License: UNKNOWN
Platform: UNKNOWN
Classifier: Programming Language :: Python :: 3
Classifier: License :: OSI Approved :: MIT License
Classifier: Operating System :: OS Independent
Classifier: Development Status :: 4 - Beta
Requires-Dist: boto3 (>=1.8.5)
Requires-Dist: Django (>=1.9)
